main.py
mseep_mcp_server_ledger-0.1.2.dist-info/METADATA
mseep_mcp_server_ledger-0.1.2.dist-info/WHEEL
mseep_mcp_server_ledger-0.1.2.dist-info/top_level.txt
mseep_mcp_server_ledger-0.1.2.dist-info/RECORD
